yoursql.py
yoursql-0.1.1.dist-info/entry_points.txt
yoursql-0.1.1.dist-info/LICENSE
yoursql-0.1.1.dist-info/WHEEL
yoursql-0.1.1.dist-info/METADATA
yoursql-0.1.1.dist-info/RECORD
